{"formInfoList":[
    {
        "qylxid": "1101",
        "qysbzt01": "",
        "qylx": "制造集团",
        "qysbzt02": "",
        "qykhxl02": "",
        "qygrqk04": "",
        "year": "2022",
        "qykhxl01": "",
        "qygrqk03": "",
        "qy": "",
        "qyscjd01": "X4pro",
        "bm": "",
        "qyscjd02": "已完工",
        "qyscjd03": 0,
        "qygyspm02": "",
        "month": "12月",
        "qygrqk02": "",
        "qygrqk01": "",
        "banji": "",
        "qygyspm01": ""
    },
    {
        "qylxid": "1101",
        "qysbzt01": "",
        "qylx": "制造集团",
        "qysbzt02": "",
        "qykhxl02": "",
        "qygrqk04": "",
        "year": "2022",
        "qykhxl01": "",
        "qygrqk03": "",
        "qy": "",
        "qyscjd01": "",
        "bm": "",
        "qyscjd02": "",
        "qyscjd03": "",
        "qygyspm02": 3700000,
        "month": "12月",
        "qygrqk02": "",
        "qygrqk01": "",
        "banji": "",
        "qygyspm01": "晶弘贸易"
    },
    {
        "qylxid": "1101",
        "qysbzt01": "",
        "qylx": "制造集团",
        "qysbzt02": "",
        "qykhxl02": "",
        "qygrqk04": "",
        "year": "2022",
        "qykhxl01": "",
        "qygrqk03": "",
        "qy": "",
        "qyscjd01": "X4MINI",
        "bm": "",
        "qyscjd02": "待生产",
        "qyscjd03": 0,
        "qygyspm02": "",
        "month": "12月",
        "qygrqk02": "",
        "qygrqk01": "",
        "banji": "",
        "qygyspm01": ""
    },
    {
        "qylxid": "1101",
        "qysbzt01": "",
        "qylx": "制造集团",
        "qysbzt02": "",
        "qykhxl02": 9264000,
        "qygrqk04": "",
        "year": "2022",
        "qykhxl01": "新锐创新销售公司",
        "qygrqk03": "",
        "qy": "",
        "qyscjd01": "",
        "bm": "",
        "qyscjd02": "",
        "qyscjd03": "",
        "qygyspm02": "",
        "month": "12月",
        "qygrqk02": "",
        "qygrqk01": "",
        "banji": "",
        "qygyspm01": ""
    },
    {
        "qylxid": "1301",
        "qysbzt01": "",
        "qylx": "经销企业",
        "qysbzt02": "",
        "qykhxl02": 18083000,
        "qygrqk04": "",
        "year": "2022",
        "qykhxl01": "跃飞智能",
        "qygrqk03": "",
        "qy": "",
        "qyscjd01": "",
        "bm": "",
        "qyscjd02": "",
        "qyscjd03": "",
        "qygyspm02": "",
        "month": "12月",
        "qygrqk02": "",
        "qygrqk01": "",
        "banji": "",
        "qygyspm01": ""
    },
    {
        "qylxid": "1301",
        "qysbzt01": "",
        "qylx": "经销企业",
        "qysbzt02": "",
        "qykhxl02": "",
        "qygrqk04": "",
        "year": "2022",
        "qykhxl01": "",
        "qygrqk03": "",
        "qy": "",
        "qyscjd01": "",
        "bm": "",
        "qyscjd02": "",
        "qyscjd03": "",
        "qygyspm02": 2000000,
        "month": "12月",
        "qygrqk02": "",
        "qygrqk01": "",
        "banji": "",
        "qygyspm01": "新源创新销售公司"
    },
    {
        "qylxid": "1101",
        "qysbzt01": "",
        "qylx": "制造集团",
        "qysbzt02": "",
        "qykhxl02": "",
        "qygrqk04": "",
        "year": "2022",
        "qykhxl01": "",
        "qygrqk03": "",
        "qy": "",
        "qyscjd01": "X4SE",
        "bm": "",
        "qyscjd02": "已完工",
        "qyscjd03": 0,
        "qygyspm02": "",
        "month": "12月",
        "qygrqk02": "",
        "qygrqk01": "",
        "banji": "",
        "qygyspm01": ""
    },
    {
        "qylxid": "1101",
        "qysbzt01": "",
        "qylx": "制造集团",
        "qysbzt02": "",
        "qykhxl02": "",
        "qygrqk04": 60,
        "year": "2022",
        "qykhxl01": "",
        "qygrqk03": 8,
        "qy": "",
        "qyscjd01": "",
        "bm": "",
        "qyscjd02": "",
        "qyscjd03": "",
        "qygyspm02": "",
        "month": "12月",
        "qygrqk02": 20,
        "qygrqk01": "中级工人",
        "banji": "",
        "qygyspm01": ""
    },
    {
        "qylxid": "1401",
        "qysbzt01": "",
        "qylx": "供应企业",
        "qysbzt02": "",
        "qykhxl02": 1500000,
        "qygrqk04": "",
        "year": "2022",
        "qykhxl01": "新捷创新科技集团",
        "qygrqk03": "",
        "qy": "",
        "qyscjd01": "",
        "bm": "",
        "qyscjd02": "",
        "qyscjd03": "",
        "qygyspm02": "",
        "month": "12月",
        "qygrqk02": "",
        "qygrqk01": "",
        "banji": "",
        "qygyspm01": ""
    },
    {
        "qylxid": "1301",
        "qysbzt01": "",
        "qylx": "经销企业",
        "qysbzt02": "",
        "qykhxl02": 25000000,
        "qygrqk04": "",
        "year": "2022",
        "qykhxl01": "启飞智能",
        "qygrqk03": "",
        "qy": "",
        "qyscjd01": "",
        "bm": "",
        "qyscjd02": "",
        "qyscjd03": "",
        "qygyspm02": "",
        "month": "12月",
        "qygrqk02": "",
        "qygrqk01": "",
        "banji": "",
        "qygyspm01": ""
    },
    {
        "qylxid": "1301",
        "qysbzt01": "",
        "qylx": "经销企业",
        "qysbzt02": "",
        "qykhxl02": "",
        "qygrqk04": "",
        "year": "2022",
        "qykhxl01": "",
        "qygrqk03": "",
        "qy": "",
        "qyscjd01": "",
        "bm": "",
        "qyscjd02": "",
        "qyscjd03": "",
        "qygyspm02": 3500000,
        "month": "12月",
        "qygrqk02": "",
        "qygrqk01": "",
        "banji": "",
        "qygyspm01": "新锐创新销售公司"
    },
    {
        "qylxid": "1101",
        "qysbzt01": "",
        "qylx": "制造集团",
        "qysbzt02": "",
        "qykhxl02": "",
        "qygrqk04": "",
        "year": "2022",
        "qykhxl01": "",
        "qygrqk03": "",
        "qy": "",
        "qyscjd01": "X4pro",
        "bm": "",
        "qyscjd02": "生产中",
        "qyscjd03": 0,
        "qygyspm02": "",
        "month": "12月",
        "qygrqk02": "",
        "qygrqk01": "",
        "banji": "",
        "qygyspm01": ""
    },
    {
        "qylxid": "1401",
        "qysbzt01": "",
        "qylx": "供应企业",
        "qysbzt02": "",
        "qykhxl02": 4000000,
        "qygrqk04": "",
        "year": "2022",
        "qykhxl01": "新锐创新科技集团",
        "qygrqk03": "",
        "qy": "",
        "qyscjd01": "",
        "bm": "",
        "qyscjd02": "",
        "qyscjd03": "",
        "qygyspm02": "",
        "month": "12月",
        "qygrqk02": "",
        "qygrqk01": "",
        "banji": "",
        "qygyspm01": ""
    },
    {
        "qylxid": "1401",
        "qysbzt01": "",
        "qylx": "供应企业",
        "qysbzt02": "",
        "qykhxl02": "",
        "qygrqk04": "",
        "year": "2022",
        "qykhxl01": "",
        "qygrqk03": "",
        "qy": "",
        "qyscjd01": "",
        "bm": "",
        "qyscjd02": "",
        "qyscjd03": "",
        "qygyspm02": 584000,
        "month": "12月",
        "qygrqk02": "",
        "qygrqk01": "",
        "banji": "",
        "qygyspm01": "西安同创"
    },
    {
        "qylxid": "1101",
        "qysbzt01": "完工",
        "qylx": "制造集团",
        "qysbzt02": 1,
        "qykhxl02": "",
        "qygrqk04": "",
        "year": "2022",
        "qykhxl01": "",
        "qygrqk03": "",
        "qy": "",
        "qyscjd01": "",
        "bm": "",
        "qyscjd02": "",
        "qyscjd03": "",
        "qygyspm02": "",
        "month": "12月",
        "qygrqk02": "",
        "qygrqk01": "",
        "banji": "",
        "qygyspm01": ""
    },
    {
        "qylxid": "1101",
        "qysbzt01": "",
        "qylx": "制造集团",
        "qysbzt02": "",
        "qykhxl02": "",
        "qygrqk04": "",
        "year": "2022",
        "qykhxl01": "",
        "qygrqk03": "",
        "qy": "",
        "qyscjd01": "",
        "bm": "",
        "qyscjd02": "",
        "qyscjd03": "",
        "qygyspm02": 1500000,
        "month": "12月",
        "qygrqk02": "",
        "qygrqk01": "",
        "banji": "",
        "qygyspm01": "星祥贸易"
    },
    {
        "qylxid": "1101",
        "qysbzt01": "",
        "qylx": "制造集团",
        "qysbzt02": "",
        "qykhxl02": "",
        "qygrqk04": "",
        "year": "2022",
        "qykhxl01": "",
        "qygrqk03": "",
        "qy": "",
        "qyscjd01": "X4MINI",
        "bm": "",
        "qyscjd02": "生产中",
        "qyscjd03": 3000,
        "qygyspm02": "",
        "month": "12月",
        "qygrqk02": "",
        "qygrqk01": "",
        "banji": "",
        "qygyspm01": ""
    },
    {
        "qylxid": "1201",
        "qysbzt01": "",
        "qylx": "销售公司",
        "qysbzt02": "",
        "qykhxl02": 2575000,
        "qygrqk04": "",
        "year": "2022",
        "qykhxl01": "辉煌商贸",
        "qygrqk03": "",
        "qy": "",
        "qyscjd01": "",
        "bm": "",
        "qyscjd02": "",
        "qyscjd03": "",
        "qygyspm02": "",
        "month": "12月",
        "qygrqk02": "",
        "qygrqk01": "",
        "banji": "",
        "qygyspm01": ""
    },
    {
        "qylxid": "1301",
        "qysbzt01": "",
        "qylx": "经销企业",
        "qysbzt02": "",
        "qykhxl02": 9083000,
        "qygrqk04": "",
        "year": "2022",
        "qykhxl01": "久天嘉兴",
        "qygrqk03": "",
        "qy": "",
        "qyscjd01": "",
        "bm": "",
        "qyscjd02": "",
        "qyscjd03": "",
        "qygyspm02": "",
        "month": "12月",
        "qygrqk02": "",
        "qygrqk01": "",
        "banji": "",
        "qygyspm01": ""
    },
    {
        "qylxid": "1401",
        "qysbzt01": "",
        "qylx": "供应企业",
        "qysbzt02": "",
        "qykhxl02": "",
        "qygrqk04": "",
        "year": "2022",
        "qykhxl01": "",
        "qygrqk03": "",
        "qy": "",
        "qyscjd01": "",
        "bm": "",
        "qyscjd02": "",
        "qyscjd03": "",
        "qygyspm02": 900000,
        "month": "12月",
        "qygrqk02": "",
        "qygrqk01": "",
        "banji": "",
        "qygyspm01": "东莞飞跃"
    },
    {
        "qylxid": "1101",
        "qysbzt01": "空闲",
        "qylx": "制造集团",
        "qysbzt02": 1,
        "qykhxl02": "",
        "qygrqk04": "",
        "year": "2022",
        "qykhxl01": "",
        "qygrqk03": "",
        "qy": "",
        "qyscjd01": "",
        "bm": "",
        "qyscjd02": "",
        "qyscjd03": "",
        "qygyspm02": "",
        "month": "12月",
        "qygrqk02": "",
        "qygrqk01": "",
        "banji": "",
        "qygyspm01": ""
    },
    {
        "qylxid": "1101",
        "qysbzt01": "",
        "qylx": "制造集团",
        "qysbzt02": "",
        "qykhxl02": "",
        "qygrqk04": "",
        "year": "2022",
        "qykhxl01": "",
        "qygrqk03": "",
        "qy": "",
        "qyscjd01": "",
        "bm": "",
        "qyscjd02": "",
        "qyscjd03": "",
        "qygyspm02": 2000000,
        "month": "12月",
        "qygrqk02": "",
        "qygrqk01": "",
        "banji": "",
        "qygyspm01": "朗兴贸易"
    },
    {
        "qylxid": "1101",
        "qysbzt01": "",
        "qylx": "制造集团",
        "qysbzt02": "",
        "qykhxl02": "",
        "qygrqk04": "",
        "year": "2022",
        "qykhxl01": "",
        "qygrqk03": "",
        "qy": "",
        "qyscjd01": "X4SE",
        "bm": "",
        "qyscjd02": "待生产",
        "qyscjd03": 0,
        "qygyspm02": "",
        "month": "12月",
        "qygrqk02": "",
        "qygrqk01": "",
        "banji": "",
        "qygyspm01": ""
    },
    {
        "qylxid": "1201",
        "qysbzt01": "",
        "qylx": "销售公司",
        "qysbzt02": "",
        "qykhxl02": 3555000,
        "qygrqk04": "",
        "year": "2022",
        "qykhxl01": "金德商贸",
        "qygrqk03": "",
        "qy": "",
        "qyscjd01": "",
        "bm": "",
        "qyscjd02": "",
        "qyscjd03": "",
        "qygyspm02": "",
        "month": "12月",
        "qygrqk02": "",
        "qygrqk01": "",
        "banji": "",
        "qygyspm01": ""
    },
    {
        "qylxid": "1301",
        "qysbzt01": "",
        "qylx": "经销企业",
        "qysbzt02": "",
        "qykhxl02": 15000000,
        "qygrqk04": "",
        "year": "2022",
        "qykhxl01": "航科百佳",
        "qygrqk03": "",
        "qy": "",
        "qyscjd01": "",
        "bm": "",
        "qyscjd02": "",
        "qyscjd03": "",
        "qygyspm02": "",
        "month": "12月",
        "qygrqk02": "",
        "qygrqk01": "",
        "banji": "",
        "qygyspm01": ""
    },
    {
        "qylxid": "1301",
        "qysbzt01": "",
        "qylx": "经销企业",
        "qysbzt02": "",
        "qykhxl02": "",
        "qygrqk04": "",
        "year": "2022",
        "qykhxl01": "",
        "qygrqk03": "",
        "qy": "",
        "qyscjd01": "",
        "bm": "",
        "qyscjd02": "",
        "qyscjd03": "",
        "qygyspm02": 1600000,
        "month": "12月",
        "qygrqk02": "",
        "qygrqk01": "",
        "banji": "",
        "qygyspm01": "新凌创新销售公司"
    },
    {
        "qylxid": "1101",
        "qysbzt01": "",
        "qylx": "制造集团",
        "qysbzt02": "",
        "qykhxl02": "",
        "qygrqk04": 0,
        "year": "2022",
        "qykhxl01": "",
        "qygrqk03": 0,
        "qy": "",
        "qyscjd01": "",
        "bm": "",
        "qyscjd02": "",
        "qyscjd03": "",
        "qygyspm02": "",
        "month": "12月",
        "qygrqk02": 0,
        "qygrqk01": "高级工人",
        "banji": "",
        "qygyspm01": ""
    },
    {
        "qylxid": "1401",
        "qysbzt01": "",
        "qylx": "供应企业",
        "qysbzt02": "",
        "qykhxl02": 1000000,
        "qygrqk04": "",
        "year": "2022",
        "qykhxl01": "新焱创新科技集团",
        "qygrqk03": "",
        "qy": "",
        "qyscjd01": "",
        "bm": "",
        "qyscjd02": "",
        "qyscjd03": "",
        "qygyspm02": "",
        "month": "12月",
        "qygrqk02": "",
        "qygrqk01": "",
        "banji": "",
        "qygyspm01": ""
    },
    {
        "qylxid": "1301",
        "qysbzt01": "",
        "qylx": "经销企业",
        "qysbzt02": "",
        "qykhxl02": 19083000,
        "qygrqk04": "",
        "year": "2022",
        "qykhxl01": " 翼航创新",
        "qygrqk03": "",
        "qy": "",
        "qyscjd01": "",
        "bm": "",
        "qyscjd02": "",
        "qyscjd03": "",
        "qygyspm02": "",
        "month": "12月",
        "qygrqk02": "",
        "qygrqk01": "",
        "banji": "",
        "qygyspm01": ""
    },
    {
        "qylxid": "1301",
        "qysbzt01": "",
        "qylx": "经销企业",
        "qysbzt02": "",
        "qykhxl02": "",
        "qygrqk04": "",
        "year": "2022",
        "qykhxl01": "",
        "qygrqk03": "",
        "qy": "",
        "qyscjd01": "",
        "bm": "",
        "qyscjd02": "",
        "qyscjd03": "",
        "qygyspm02": 3000000,
        "month": "12月",
        "qygrqk02": "",
        "qygrqk01": "",
        "banji": "",
        "qygyspm01": "新捷创新销售公司"
    },
    {
        "qylxid": "1101",
        "qysbzt01": "",
        "qylx": "制造集团",
        "qysbzt02": "",
        "qykhxl02": "",
        "qygrqk04": "",
        "year": "2022",
        "qykhxl01": "",
        "qygrqk03": "",
        "qy": "",
        "qyscjd01": "X4MINI",
        "bm": "",
        "qyscjd02": "已完工",
        "qyscjd03": 4500,
        "qygyspm02": "",
        "month": "12月",
        "qygrqk02": "",
        "qygrqk01": "",
        "banji": "",
        "qygyspm01": ""
    },
    {
        "qylxid": "1101",
        "qysbzt01": "",
        "qylx": "制造集团",
        "qysbzt02": "",
        "qykhxl02": "",
        "qygrqk04": 70,
        "year": "2022",
        "qykhxl01": "",
        "qygrqk03": 6,
        "qy": "",
        "qyscjd01": "",
        "bm": "",
        "qyscjd02": "",
        "qyscjd03": "",
        "qygyspm02": "",
        "month": "12月",
        "qygrqk02": 20,
        "qygrqk01": "初级工人",
        "banji": "",
        "qygyspm01": ""
    },
    {
        "qylxid": "1401",
        "qysbzt01": "",
        "qylx": "供应企业",
        "qysbzt02": "",
        "qykhxl02": 3500000,
        "qygrqk04": "",
        "year": "2022",
        "qykhxl01": "新阳创新科技集团",
        "qygrqk03": "",
        "qy": "",
        "qyscjd01": "",
        "bm": "",
        "qyscjd02": "",
        "qyscjd03": "",
        "qygyspm02": "",
        "month": "12月",
        "qygrqk02": "",
        "qygrqk01": "",
        "banji": "",
        "qygyspm01": ""
    },
    {
        "qylxid": "1201",
        "qysbzt01": "",
        "qylx": "销售公司",
        "qysbzt02": "",
        "qykhxl02": 2175000,
        "qygrqk04": "",
        "year": "2022",
        "qykhxl01": "林枫商贸",
        "qygrqk03": "",
        "qy": "",
        "qyscjd01": "",
        "bm": "",
        "qyscjd02": "",
        "qyscjd03": "",
        "qygyspm02": "",
        "month": "12月",
        "qygrqk02": "",
        "qygrqk01": "",
        "banji": "",
        "qygyspm01": ""
    },
    {
        "qylxid": "1201",
        "qysbzt01": "",
        "qylx": "销售公司",
        "qysbzt02": "",
        "qykhxl02": "",
        "qygrqk04": "",
        "year": "2022",
        "qykhxl01": "",
        "qygrqk03": "",
        "qy": "",
        "qyscjd01": "",
        "bm": "",
        "qyscjd02": "",
        "qyscjd03": "",
        "qygyspm02": 9550000,
        "month": "12月",
        "qygrqk02": "",
        "qygrqk01": "",
        "banji": "",
        "qygyspm01": "新锐创新科技集团"
    },
    {
        "qylxid": "1101",
        "qysbzt01": "",
        "qylx": "制造集团",
        "qysbzt02": "",
        "qykhxl02": "",
        "qygrqk04": "",
        "year": "2022",
        "qykhxl01": "",
        "qygrqk03": "",
        "qy": "",
        "qyscjd01": "X4SE",
        "bm": "",
        "qyscjd02": "生产中",
        "qyscjd03": 0,
        "qygyspm02": "",
        "month": "12月",
        "qygrqk02": "",
        "qygrqk01": "",
        "banji": "",
        "qygyspm01": ""
    },
    {
        "qylxid": "1401",
        "qysbzt01": "",
        "qylx": "供应企业",
        "qysbzt02": "",
        "qykhxl02": 1500000,
        "qygrqk04": "",
        "year": "2022",
        "qykhxl01": "新源创新科技集团",
        "qygrqk03": "",
        "qy": "",
        "qyscjd01": "",
        "bm": "",
        "qyscjd02": "",
        "qyscjd03": "",
        "qygyspm02": "",
        "month": "12月",
        "qygrqk02": "",
        "qygrqk01": "",
        "banji": "",
        "qygyspm01": ""
    },
    {
        "qylxid": "1401",
        "qysbzt01": "",
        "qylx": "供应企业",
        "qysbzt02": "",
        "qykhxl02": "",
        "qygrqk04": "",
        "year": "2022",
        "qykhxl01": "",
        "qygrqk03": "",
        "qy": "",
        "qyscjd01": "",
        "bm": "",
        "qyscjd02": "",
        "qyscjd03": "",
        "qygyspm02": 880000,
        "month": "12月",
        "qygrqk02": "",
        "qygrqk01": "",
        "banji": "",
        "qygyspm01": "安徽五金"
    },
    {
        "qylxid": "1101",
        "qysbzt01": "生产中",
        "qylx": "制造集团",
        "qysbzt02": 6,
        "qykhxl02": "",
        "qygrqk04": "",
        "year": "2022",
        "qykhxl01": "",
        "qygrqk03": "",
        "qy": "",
        "qyscjd01": "",
        "bm": "",
        "qyscjd02": "",
        "qyscjd03": "",
        "qygyspm02": "",
        "month": "12月",
        "qygrqk02": "",
        "qygrqk01": "",
        "banji": "",
        "qygyspm01": ""
    },
    {
        "qylxid": "1101",
        "qysbzt01": "",
        "qylx": "制造集团",
        "qysbzt02": "",
        "qykhxl02": "",
        "qygrqk04": "",
        "year": "2022",
        "qykhxl01": "",
        "qygrqk03": "",
        "qy": "",
        "qyscjd01": "",
        "bm": "",
        "qyscjd02": "",
        "qyscjd03": "",
        "qygyspm02": 1825000,
        "month": "12月",
        "qygrqk02": "",
        "qygrqk01": "",
        "banji": "",
        "qygyspm01": "天凯贸易"
    },
    {
        "qylxid": "1101",
        "qysbzt01": "",
        "qylx": "制造集团",
        "qysbzt02": "",
        "qykhxl02": "",
        "qygrqk04": "",
        "year": "2022",
        "qykhxl01": "",
        "qygrqk03": "",
        "qy": "",
        "qyscjd01": "X4pro",
        "bm": "",
        "qyscjd02": "待生产",
        "qyscjd03": 0,
        "qygyspm02": "",
        "month": "12月",
        "qygrqk02": "",
        "qygrqk01": "",
        "banji": "",
        "qygyspm01": ""
    },
    {
        "qylxid": "1201",
        "qysbzt01": "",
        "qylx": "销售公司",
        "qysbzt02": "",
        "qykhxl02": 2795000,
        "qygrqk04": "",
        "year": "2022",
        "qykhxl01": "浩佳商贸",
        "qygrqk03": "",
        "qy": "",
        "qyscjd01": "",
        "bm": "",
        "qyscjd02": "",
        "qyscjd03": "",
        "qygyspm02": "",
        "month": "12月",
        "qygrqk02": "",
        "qygrqk01": "",
        "banji": "",
        "qygyspm01": ""
    },
    {
        "qylxid": "1301",
        "qysbzt01": "",
        "qylx": "经销企业",
        "qysbzt02": "",
        "qykhxl02": 11083000,
        "qygrqk04": "",
        "year": "2022",
        "qykhxl01": "瀚翔天驰",
        "qygrqk03": "",
        "qy": "",
        "qyscjd01": "",
        "bm": "",
        "qyscjd02": "",
        "qyscjd03": "",
        "qygyspm02": "",
        "month": "12月",
        "qygrqk02": "",
        "qygrqk01": "",
        "banji": "",
        "qygyspm01": ""
    },
    {
        "qylxid": "1401",
        "qysbzt01": "",
        "qylx": "供应企业",
        "qysbzt02": "",
        "qykhxl02": "",
        "qygrqk04": "",
        "year": "2022",
        "qykhxl01": "",
        "qygrqk03": "",
        "qy": "",
        "qyscjd01": "",
        "bm": "",
        "qyscjd02": "",
        "qyscjd03": "",
        "qygyspm02": 960000,
        "month": "12月",
        "qygrqk02": "",
        "qygrqk01": "",
        "banji": "",
        "qygyspm01": "山东精航"
    }
]}